ingestify/__init__.py
ingestify/cmdline.py
ingestify/exceptions.py
ingestify/main.py
ingestify/server.py
ingestify/source_base.py
ingestify/utils.py
ingestify/application/__init__.py
ingestify/application/dataset_store.py
ingestify/application/ingestion_engine.py
ingestify/application/loader.py
ingestify/application/secrets_manager.py
ingestify/domain/__init__.py
ingestify/domain/models/__init__.py
ingestify/domain/models/base.py
ingestify/domain/models/data_spec_version_collection.py
ingestify/domain/models/fetch_policy.py
ingestify/domain/models/sink.py
ingestify/domain/models/source.py
ingestify/domain/models/timing.py
ingestify/domain/models/dataset/__init__.py
ingestify/domain/models/dataset/collection.py
ingestify/domain/models/dataset/collection_metadata.py
ingestify/domain/models/dataset/dataset.py
ingestify/domain/models/dataset/dataset_repository.py
ingestify/domain/models/dataset/dataset_state.py
ingestify/domain/models/dataset/events.py
ingestify/domain/models/dataset/file.py
ingestify/domain/models/dataset/file_collection.py
ingestify/domain/models/dataset/file_repository.py
ingestify/domain/models/dataset/identifier.py
ingestify/domain/models/dataset/revision.py
ingestify/domain/models/dataset/selector.py
ingestify/domain/models/event/__init__.py
ingestify/domain/models/event/_old_event.py
ingestify/domain/models/event/dispatcher.py
ingestify/domain/models/event/domain_event.py
ingestify/domain/models/event/event_bus.py
ingestify/domain/models/event/publisher.py
ingestify/domain/models/event/subscriber.py
ingestify/domain/models/ingestion/__init__.py
ingestify/domain/models/ingestion/ingestion_job.py
ingestify/domain/models/ingestion/ingestion_job_summary.py
ingestify/domain/models/ingestion/ingestion_plan.py
ingestify/domain/models/resources/__init__.py
ingestify/domain/models/resources/dataset_resource.py
ingestify/domain/models/task/__init__.py
ingestify/domain/models/task/set.py
ingestify/domain/models/task/task.py
ingestify-0.9.4.dist-info/METADATA
ingestify-0.9.4.dist-info/WHEEL
ingestify-0.9.4.dist-info/entry_points.txt
ingestify-0.9.4.dist-info/top_level.txt
ingestify-0.9.4.dist-info/RECORD
