Metadata-Version: 2.4
Name: ingestify
Version: 0.9.4
Summary: Data Ingestion Framework
Author: Koen Vossen
Author-email: info@koenvossen.nl
License: AGPL
Requires-Dist: requests<3,>=2.0.0
Requires-Dist: SQLAlchemy<3,>=2
Requires-Dist: click>=8
Requires-Dist: python-dotenv
Requires-Dist: pyaml_env
Requires-Dist: boto3
Requires-Dist: pydantic>=2.0.0
Provides-Extra: test
Requires-Dist: pytest<7,>=6.2.5; extra == "test"
Requires-Dist: pytz; extra == "test"
Dynamic: author
Dynamic: author-email
Dynamic: description
Dynamic: description-content-type
Dynamic: license
Dynamic: provides-extra
Dynamic: requires-dist
Dynamic: summary
